mutwo/common_generators/__init__.py
mutwo/common_generators/brown.py
mutwo/common_generators/brun.py
mutwo/common_generators/chomksy.py
mutwo/common_generators/constants.py
mutwo/common_generators/edwards.py
mutwo/common_generators/generic.py
mutwo/common_generators/gray.py
mutwo/common_generators/koenig.py
mutwo/common_generators/lehmer.py
mutwo/common_generators/schillinger.py
mutwo/common_generators/toussaint.py
mutwo/common_utilities/__init__.py
mutwo/common_utilities/exceptions.py
mutwo/common_version/__init__.py
mutwo.common-0.12.1.dist-info/LICENSE
mutwo.common-0.12.1.dist-info/METADATA
mutwo.common-0.12.1.dist-info/WHEEL
mutwo.common-0.12.1.dist-info/top_level.txt
mutwo.common-0.12.1.dist-info/RECORD
